MANIFEST.in
README.md
setup.py
srkSUB/__init__.py
srkSUB/base.py
srkSUB/substrate.py
srkSUB/test.py
srkSUB.egg-info/PKG-INFO
srkSUB.egg-info/SOURCES.txt
srkSUB.egg-info/dependency_links.txt
srkSUB.egg-info/requires.txt
srkSUB.egg-info/top_level.txt
srkSUB/types/cru.json
srkSUB/types/khala.json