Metadata-Version: 1.0
Name: srkSUB
Version: 1.6
Summary: Support More Substrate Chain Package
Home-page: https://github.com/Yxiaoyang/srkSUB
Author: srank
Author-email: 625593240@qq.com
License: GNU General Public License v3.0
Platform: UNKNOWN
